<annotation><folder>images</folder><filename>anonymous_003-007-1142-00_1732596329973_Mandibular_View.jpg</filename><size><width>2556</width><height>1916</height><depth>3</depth></size><object><name>D</name><pose>Unspecified</pose><truncated>0</truncated><difficult>0</difficult><bndbox><xmin>71</xmin><ymin>297</ymin><xmax>427</xmax><ymax>684</ymax></bndbox></object><object><name>D</name><pose>Unspecified</pose><truncated>0</truncated><difficult>0</difficult><bndbox><xmin>106</xmin><ymin>597</ymin><xmax>549</xmax><ymax>1016</ymax></bndbox></object></annotation>