<annotation><folder>images</folder><filename>anonymous_003-007-870-00_1730264018655_Mandibular_View.jpg</filename><size><width>1988</width><height>1325</height><depth>3</depth></size><object><name>D</name><pose>Unspecified</pose><truncated>0</truncated><difficult>0</difficult><bndbox><xmin>30</xmin><ymin>146</ymin><xmax>373</xmax><ymax>471</ymax></bndbox></object><object><name>D</name><pose>Unspecified</pose><truncated>0</truncated><difficult>0</difficult><bndbox><xmin>1671</xmin><ymin>160</ymin><xmax>1959</xmax><ymax>507</ymax></bndbox></object><object><name>d</name><pose>Unspecified</pose><truncated>0</truncated><difficult>0</difficult><bndbox><xmin>166</xmin><ymin>446</ymin><xmax>480</xmax><ymax>757</ymax></bndbox></object><object><name>d</name><pose>Unspecified</pose><truncated>0</truncated><difficult>0</difficult><bndbox><xmin>1557</xmin><ymin>448</ymin><xmax>1853</xmax><ymax>794</ymax></bndbox></object><object><name>d</name><pose>Unspecified</pose><truncated>0</truncated><difficult>0</difficult><bndbox><xmin>248</xmin><ymin>742</ymin><xmax>544</xmax><ymax>951</ymax></bndbox></object><object><name>d</name><pose>Unspecified</pose><truncated>0</truncated><difficult>0</difficult><bndbox><xmin>1459</xmin><ymin>723</ymin><xmax>1737</xmax><ymax>967</ymax></bndbox></object></annotation>