<annotation><folder>images</folder><filename>anonymous_003_007_450_00_1728541413504_Mandibular_View.jpg</filename><size><width>1955</width><height>1098</height><depth>3</depth></size><object><name>D</name><pose>Unspecified</pose><truncated>0</truncated><difficult>0</difficult><bndbox><xmin>101</xmin><ymin>100</ymin><xmax>351</xmax><ymax>336</ymax></bndbox></object><object><name>D</name><pose>Unspecified</pose><truncated>0</truncated><difficult>0</difficult><bndbox><xmin>81</xmin><ymin>302</ymin><xmax>410</xmax><ymax>565</ymax></bndbox></object><object><name>D</name><pose>Unspecified</pose><truncated>0</truncated><difficult>0</difficult><bndbox><xmin>1571</xmin><ymin>37</ymin><xmax>1858</xmax><ymax>273</ymax></bndbox></object><object><name>D</name><pose>Unspecified</pose><truncated>0</truncated><difficult>0</difficult><bndbox><xmin>1475</xmin><ymin>232</ymin><xmax>1801</xmax><ymax>547</ymax></bndbox></object></annotation>