<annotation><folder>images</folder><filename>anonymous_003-008-1222-00_1732876045526_Mandibular_View.jpg</filename><size><width>1198</width><height>898</height><depth>3</depth></size><object><name>D</name><pose>Unspecified</pose><truncated>0</truncated><difficult>0</difficult><bndbox><xmin>66</xmin><ymin>198</ymin><xmax>291</xmax><ymax>388</ymax></bndbox></object><object><name>d</name><pose>Unspecified</pose><truncated>0</truncated><difficult>0</difficult><bndbox><xmin>136</xmin><ymin>360</ymin><xmax>339</xmax><ymax>583</ymax></bndbox></object><object><name>D</name><pose>Unspecified</pose><truncated>0</truncated><difficult>0</difficult><bndbox><xmin>928</xmin><ymin>226</ymin><xmax>1139</xmax><ymax>419</ymax></bndbox></object><object><name>d</name><pose>Unspecified</pose><truncated>0</truncated><difficult>0</difficult><bndbox><xmin>912</xmin><ymin>389</ymin><xmax>1105</xmax><ymax>598</ymax></bndbox></object><object><name>d</name><pose>Unspecified</pose><truncated>0</truncated><difficult>0</difficult><bndbox><xmin>876</xmin><ymin>512</ymin><xmax>1023</xmax><ymax>686</ymax></bndbox></object></annotation>