<annotation><folder>images</folder><filename>anonymous_003-008-778-00_1729764871150_Mandibular_View.jpg</filename><size><width>1163</width><height>871</height><depth>3</depth></size><object><name>D</name><pose>Unspecified</pose><truncated>0</truncated><difficult>0</difficult><bndbox><xmin>884</xmin><ymin>278</ymin><xmax>1077</xmax><ymax>448</ymax></bndbox></object><object><name>D</name><pose>Unspecified</pose><truncated>0</truncated><difficult>0</difficult><bndbox><xmin>88</xmin><ymin>228</ymin><xmax>284</xmax><ymax>404</ymax></bndbox></object></annotation>