<annotation><folder>images</folder><filename>anonymous_003-009-707-00_1729343513251_Mandibular_View.jpg</filename><size><width>1981</width><height>1321</height><depth>3</depth></size><object><name>D</name><pose>Unspecified</pose><truncated>0</truncated><difficult>0</difficult><bndbox><xmin>1529</xmin><ymin>60</ymin><xmax>1868</xmax><ymax>276</ymax></bndbox></object><object><name>D</name><pose>Unspecified</pose><truncated>0</truncated><difficult>0</difficult><bndbox><xmin>70</xmin><ymin>65</ymin><xmax>359</xmax><ymax>279</ymax></bndbox></object><object><name>D</name><pose>Unspecified</pose><truncated>0</truncated><difficult>0</difficult><bndbox><xmin>1492</xmin><ymin>258</ymin><xmax>1835</xmax><ymax>532</ymax></bndbox></object></annotation>