<annotation><folder>images</folder><filename>anonymous-mandibularView-1726818342880.jpg</filename><size><width>1813</width><height>1813</height><depth>3</depth></size><object><name>D</name><pose>Unspecified</pose><truncated>0</truncated><difficult>0</difficult><bndbox><xmin>1521</xmin><ymin>685</ymin><xmax>1716</xmax><ymax>850</ymax></bndbox></object><object><name>D</name><pose>Unspecified</pose><truncated>0</truncated><difficult>0</difficult><bndbox><xmin>1446</xmin><ymin>816</ymin><xmax>1727</xmax><ymax>1031</ymax></bndbox></object><object><name>D</name><pose>Unspecified</pose><truncated>0</truncated><difficult>0</difficult><bndbox><xmin>127</xmin><ymin>673</ymin><xmax>354</xmax><ymax>856</ymax></bndbox></object><object><name>D</name><pose>Unspecified</pose><truncated>0</truncated><difficult>0</difficult><bndbox><xmin>173</xmin><ymin>812</ymin><xmax>464</xmax><ymax>1027</ymax></bndbox></object></annotation>