<annotation><folder>images</folder><filename>anonymous-mandibularView-1727868418747.jpg</filename><size><width>1617</width><height>1212</height><depth>3</depth></size><object><name>D</name><pose>Unspecified</pose><truncated>0</truncated><difficult>0</difficult><bndbox><xmin>1284</xmin><ymin>211</ymin><xmax>1554</xmax><ymax>460</ymax></bndbox></object><object><name>D</name><pose>Unspecified</pose><truncated>0</truncated><difficult>0</difficult><bndbox><xmin>72</xmin><ymin>229</ymin><xmax>334</xmax><ymax>490</ymax></bndbox></object><object><name>D</name><pose>Unspecified</pose><truncated>0</truncated><difficult>0</difficult><bndbox><xmin>137</xmin><ymin>619</ymin><xmax>394</xmax><ymax>811</ymax></bndbox></object><object><name>D</name><pose>Unspecified</pose><truncated>0</truncated><difficult>0</difficult><bndbox><xmin>1191</xmin><ymin>399</ymin><xmax>1495</xmax><ymax>675</ymax></bndbox></object><object><name>D</name><pose>Unspecified</pose><truncated>0</truncated><difficult>0</difficult><bndbox><xmin>1145</xmin><ymin>593</ymin><xmax>1390</xmax><ymax>796</ymax></bndbox></object></annotation>