<annotation><folder>images</folder><filename>anonymous_003_007_512_00_1728719966330_Left_Lateral_View.jpg</filename><size><width>1374</width><height>1374</height><depth>3</depth></size><object><name>D</name><pose>Unspecified</pose><truncated>0</truncated><difficult>0</difficult><bndbox><xmin>847</xmin><ymin>582</ymin><xmax>1180</xmax><ymax>826</ymax></bndbox></object><object><name>D</name><pose>Unspecified</pose><truncated>0</truncated><difficult>0</difficult><bndbox><xmin>1138</xmin><ymin>570</ymin><xmax>1328</xmax><ymax>761</ymax></bndbox></object></annotation>