<annotation><folder>images</folder><filename>anonymous-maxillaryView-1726839309284.jpg</filename><size><width>2357</width><height>1768</height><depth>3</depth></size><object><name>D</name><pose>Unspecified</pose><truncated>0</truncated><difficult>0</difficult><bndbox><xmin>1682</xmin><ymin>698</ymin><xmax>2072</xmax><ymax>915</ymax></bndbox></object><object><name>D</name><pose>Unspecified</pose><truncated>0</truncated><difficult>0</difficult><bndbox><xmin>1694</xmin><ymin>873</ymin><xmax>2038</xmax><ymax>1019</ymax></bndbox></object><object><name>D</name><pose>Unspecified</pose><truncated>0</truncated><difficult>0</difficult><bndbox><xmin>1644</xmin><ymin>967</ymin><xmax>2060</xmax><ymax>1168</ymax></bndbox></object><object><name>D</name><pose>Unspecified</pose><truncated>0</truncated><difficult>0</difficult><bndbox><xmin>30</xmin><ymin>872</ymin><xmax>540</xmax><ymax>1156</ymax></bndbox></object></annotation>