<annotation><folder>images</folder><filename>anonymous_003-008-1205-01_1732794208125_Mandibular_View.jpg</filename><size><width>1872</width><height>1051</height><depth>3</depth></size><object><name>D</name><pose>Unspecified</pose><truncated>0</truncated><difficult>0</difficult><bndbox><xmin>223</xmin><ymin>67</ymin><xmax>479</xmax><ymax>266</ymax></bndbox></object><object><name>D</name><pose>Unspecified</pose><truncated>0</truncated><difficult>0</difficult><bndbox><xmin>1337</xmin><ymin>116</ymin><xmax>1589</xmax><ymax>342</ymax></bndbox></object></annotation>