<annotation><folder>images</folder><filename>anonymous_003_103_323_01_1727949601502_Mandibular_View.jpg</filename><size><width>1589</width><height>1191</height><depth>3</depth></size><object><name>D</name><pose>Unspecified</pose><truncated>0</truncated><difficult>0</difficult><bndbox><xmin>27</xmin><ymin>289</ymin><xmax>276</xmax><ymax>513</ymax></bndbox></object><object><name>D</name><pose>Unspecified</pose><truncated>0</truncated><difficult>0</difficult><bndbox><xmin>1167</xmin><ymin>495</ymin><xmax>1427</xmax><ymax>732</ymax></bndbox></object></annotation>