<annotation><folder>images</folder><filename>anonymous_003-008-652-00_1729170164776_Maxillary_Occlusal_View.jpg</filename><size><width>1251</width><height>938</height><depth>3</depth></size><object><name>D</name><pose>Unspecified</pose><truncated>0</truncated><difficult>0</difficult><bndbox><xmin>85</xmin><ymin>357</ymin><xmax>284</xmax><ymax>497</ymax></bndbox></object><object><name>D</name><pose>Unspecified</pose><truncated>0</truncated><difficult>0</difficult><bndbox><xmin>30</xmin><ymin>465</ymin><xmax>258</xmax><ymax>654</ymax></bndbox></object><object><name>D</name><pose>Unspecified</pose><truncated>0</truncated><difficult>0</difficult><bndbox><xmin>33</xmin><ymin>629</ymin><xmax>255</xmax><ymax>740</ymax></bndbox></object><object><name>D</name><pose>Unspecified</pose><truncated>0</truncated><difficult>0</difficult><bndbox><xmin>938</xmin><ymin>272</ymin><xmax>1130</xmax><ymax>403</ymax></bndbox></object><object><name>D</name><pose>Unspecified</pose><truncated>0</truncated><difficult>0</difficult><bndbox><xmin>984</xmin><ymin>380</ymin><xmax>1173</xmax><ymax>491</ymax></bndbox></object><object><name>D</name><pose>Unspecified</pose><truncated>0</truncated><difficult>0</difficult><bndbox><xmin>995</xmin><ymin>481</ymin><xmax>1219</xmax><ymax>656</ymax></bndbox></object><object><name>D</name><pose>Unspecified</pose><truncated>0</truncated><difficult>0</difficult><bndbox><xmin>998</xmin><ymin>638</ymin><xmax>1190</xmax><ymax>751</ymax></bndbox></object></annotation>