<annotation><folder>images</folder><filename>anonymous_003-007-918-01_1730692542165_Maxillary_Occlusal_View.jpg</filename><size><width>3431</width><height>2572</height><depth>3</depth></size><object><name>D</name><pose>Unspecified</pose><truncated>0</truncated><difficult>0</difficult><bndbox><xmin>224</xmin><ymin>1642</ymin><xmax>889</xmax><ymax>2155</ymax></bndbox></object><object><name>D</name><pose>Unspecified</pose><truncated>0</truncated><difficult>0</difficult><bndbox><xmin>2302</xmin><ymin>1655</ymin><xmax>2967</xmax><ymax>2142</ymax></bndbox></object><object><name>D</name><pose>Unspecified</pose><truncated>0</truncated><difficult>0</difficult><bndbox><xmin>315</xmin><ymin>1316</ymin><xmax>911</xmax><ymax>1690</ymax></bndbox></object></annotation>