<annotation><folder>images</folder><filename>anonymous_003-008-762-01_1729680417375_Maxillary_Occlusal_View.jpg</filename><size><width>1495</width><height>1121</height><depth>3</depth></size><object><name>D</name><pose>Unspecified</pose><truncated>0</truncated><difficult>0</difficult><bndbox><xmin>237</xmin><ymin>373</ymin><xmax>466</xmax><ymax>533</ymax></bndbox></object><object><name>D</name><pose>Unspecified</pose><truncated>0</truncated><difficult>0</difficult><bndbox><xmin>166</xmin><ymin>498</ymin><xmax>395</xmax><ymax>650</ymax></bndbox></object><object><name>D</name><pose>Unspecified</pose><truncated>0</truncated><difficult>0</difficult><bndbox><xmin>78</xmin><ymin>614</ymin><xmax>349</xmax><ymax>862</ymax></bndbox></object><object><name>D</name><pose>Unspecified</pose><truncated>0</truncated><difficult>0</difficult><bndbox><xmin>20</xmin><ymin>791</ymin><xmax>274</xmax><ymax>993</ymax></bndbox></object><object><name>D</name><pose>Unspecified</pose><truncated>0</truncated><difficult>0</difficult><bndbox><xmin>1234</xmin><ymin>702</ymin><xmax>1478</xmax><ymax>908</ymax></bndbox></object><object><name>D</name><pose>Unspecified</pose><truncated>0</truncated><difficult>0</difficult><bndbox><xmin>1249</xmin><ymin>897</ymin><xmax>1468</xmax><ymax>1045</ymax></bndbox></object></annotation>